krmd/__init__.py
krmd/main.py
krmd/controllers/__init__.py
krmd/controllers/base.py
krmd/controllers/commands.py
krmd/core/__init__.py
krmd/core/exc.py
krmd/core/version.py
krmd/ext/__init__.py
krmd/plugins/__init__.py
krmd/templates/__init__.py
krmd/templates/command1.jinja2
krmd/templates/commands/list.jinja2
krmd-0.0.1.dev20220321184921.dist-info/LICENSE
krmd-0.0.1.dev20220321184921.dist-info/LICENSE.md
krmd-0.0.1.dev20220321184921.dist-info/METADATA
krmd-0.0.1.dev20220321184921.dist-info/WHEEL
krmd-0.0.1.dev20220321184921.dist-info/entry_points.txt
krmd-0.0.1.dev20220321184921.dist-info/top_level.txt
krmd-0.0.1.dev20220321184921.dist-info/RECORD
