Metadata-Version: 2.1
Name: krmd
Version: 0.0.1.dev20220321184921
Summary: Simple command reminder application
Home-page: https://github.com/keremdemirtrk/krmd
Author: Kerem Demirturk
Author-email: keremdemirtrk@gmail.com
License: GNU General Public License version 3
Platform: UNKNOWN
License-File: LICENSE
License-File: LICENSE.md
